<?xml version="1.0" encoding="utf-8" ?>
<c2layout>
    <name>Game Quiz Layout</name>
    <sid>589103509032944</sid>
    <event-sheet>Game Quiz Event</event-sheet>
    <size>
        <width>720</width>
        <height>1280</height>
    </size>
    <margins>
        <horizontal>500</horizontal>
        <vertical>500</vertical>
    </margins>
    <unbounded-scrolling>0</unbounded-scrolling>
    <layers>
        <layer name="Layer 0" sid="501623174767132">
            <initially-visible>1</initially-visible>
            <background-color>255,255,255</background-color>
            <transparent>0</transparent>
            <parallax>
                <x>1</x>
                <y>1</y>
            </parallax>
            <zoom-rate>1</zoom-rate>
            <opacity>1</opacity>
            <force-own-texture>0</force-own-texture>
            <global>0</global>
            <use-render-cells>0</use-render-cells>
            <blend-mode>0</blend-mode>
            <effect-fallback>0</effect-fallback>
            <instances>
                <instance type="TiledBackground8" uid="2">
                    <properties>
                        <initial-visibility>Visible</initial-visibility>
                        <hotspot>Top-left</hotspot>
                    </properties>
                    <blend-mode>0</blend-mode>
                    <effect-fallback>0</effect-fallback>
                    <world>
                        <x>0</x>
                        <y>0</y>
                        <z>0</z>
                        <width>720</width>
                        <height>1280</height>
                        <depth>0</depth>
                        <hotspotX>0</hotspotX>
                        <hotspotY>0</hotspotY>
                        <angle>0</angle>
                        <opacity>1</opacity>
                    </world>
                </instance>
                <instance type="BackPergunta1" uid="10">
                    <properties>
                        <initial-visibility>Visible</initial-visibility>
                        <initial-animation>Default</initial-animation>
                        <initial-frame>0</initial-frame>
                        <collisions>Enabled</collisions>
                    </properties>
                    <blend-mode>0</blend-mode>
                    <effect-fallback>0</effect-fallback>
                    <world>
                        <x>362</x>
                        <y>292</y>
                        <z>0</z>
                        <width>616</width>
                        <height>374</height>
                        <depth>0</depth>
                        <hotspotX>0.5</hotspotX>
                        <hotspotY>0.5</hotspotY>
                        <angle>0</angle>
                        <opacity>1</opacity>
                    </world>
                </instance>
                <instance type="BackPergunta1" uid="11">
                    <properties>
                        <initial-visibility>Visible</initial-visibility>
                        <initial-animation>Default</initial-animation>
                        <initial-frame>0</initial-frame>
                        <collisions>Enabled</collisions>
                    </properties>
                    <blend-mode>0</blend-mode>
                    <effect-fallback>0</effect-fallback>
                    <world>
                        <x>362</x>
                        <y>585</y>
                        <z>0</z>
                        <width>616</width>
                        <height>110</height>
                        <depth>0</depth>
                        <hotspotX>0.5</hotspotX>
                        <hotspotY>0.5</hotspotY>
                        <angle>0</angle>
                        <opacity>1</opacity>
                    </world>
                </instance>
                <instance type="BackPergunta1" uid="12">
                    <properties>
                        <initial-visibility>Visible</initial-visibility>
                        <initial-animation>Default</initial-animation>
                        <initial-frame>0</initial-frame>
                        <collisions>Enabled</collisions>
                    </properties>
                    <blend-mode>0</blend-mode>
                    <effect-fallback>0</effect-fallback>
                    <world>
                        <x>362</x>
                        <y>713</y>
                        <z>0</z>
                        <width>616</width>
                        <height>110</height>
                        <depth>0</depth>
                        <hotspotX>0.5</hotspotX>
                        <hotspotY>0.5</hotspotY>
                        <angle>0</angle>
                        <opacity>1</opacity>
                    </world>
                </instance>
                <instance type="BackPergunta1" uid="14">
                    <properties>
                        <initial-visibility>Visible</initial-visibility>
                        <initial-animation>Default</initial-animation>
                        <initial-frame>0</initial-frame>
                        <collisions>Enabled</collisions>
                    </properties>
                    <blend-mode>0</blend-mode>
                    <effect-fallback>0</effect-fallback>
                    <world>
                        <x>360</x>
                        <y>846</y>
                        <z>0</z>
                        <width>616</width>
                        <height>110</height>
                        <depth>0</depth>
                        <hotspotX>0.5</hotspotX>
                        <hotspotY>0.5</hotspotY>
                        <angle>0</angle>
                        <opacity>1</opacity>
                    </world>
                </instance>
                <instance type="Sprite2" uid="15">
                    <properties>
                        <initial-visibility>Visible</initial-visibility>
                        <initial-animation>Default</initial-animation>
                        <initial-frame>0</initial-frame>
                        <collisions>Enabled</collisions>
                    </properties>
                    <blend-mode>0</blend-mode>
                    <effect-fallback>0</effect-fallback>
                    <world>
                        <x>161</x>
                        <y>313</y>
                        <z>0</z>
                        <width>268</width>
                        <height>265</height>
                        <depth>0</depth>
                        <hotspotX>0.5</hotspotX>
                        <hotspotY>0.5</hotspotY>
                        <angle>0</angle>
                        <opacity>1</opacity>
                    </world>
                </instance>
                <instance type="Sprite3" uid="16">
                    <properties>
                        <initial-visibility>Visible</initial-visibility>
                        <initial-animation>Default</initial-animation>
                        <initial-frame>0</initial-frame>
                        <collisions>Enabled</collisions>
                    </properties>
                    <blend-mode>0</blend-mode>
                    <effect-fallback>0</effect-fallback>
                    <world>
                        <x>352</x>
                        <y>85</y>
                        <z>0</z>
                        <width>337</width>
                        <height>80</height>
                        <depth>0</depth>
                        <hotspotX>0.500632107</hotspotX>
                        <hotspotY>0.502415478</hotspotY>
                        <angle>0</angle>
                        <opacity>1</opacity>
                    </world>
                </instance>
                <instance type="Pergunta" uid="8">
                    <properties>
                        <text></text>
                        <initial-visibility>Visible</initial-visibility>
                        <font>Century Gothic,-29,700,0</font>
                        <color>0,0,0</color>
                        <horizontal-alignment>Center</horizontal-alignment>
                        <vertical-alignment>Center</vertical-alignment>
                        <hotspot>Center</hotspot>
                        <wrapping>Word</wrapping>
                        <line-height>0</line-height>
                    </properties>
                    <blend-mode>0</blend-mode>
                    <effect-fallback>0</effect-fallback>
                    <world>
                        <x>461</x>
                        <y>295</y>
                        <z>0</z>
                        <width>371</width>
                        <height>303</height>
                        <depth>0</depth>
                        <hotspotX>0.5</hotspotX>
                        <hotspotY>0.5</hotspotY>
                        <angle>0</angle>
                        <opacity>1</opacity>
                    </world>
                </instance>
                <instance type="Resposta2" uid="17">
                    <properties>
                        <text></text>
                        <initial-visibility>Visible</initial-visibility>
                        <font>Century Gothic,-24,400,0</font>
                        <color>0,0,0</color>
                        <horizontal-alignment>Center</horizontal-alignment>
                        <vertical-alignment>Center</vertical-alignment>
                        <hotspot>Center</hotspot>
                        <wrapping>Word</wrapping>
                        <line-height>0</line-height>
                    </properties>
                    <blend-mode>0</blend-mode>
                    <effect-fallback>0</effect-fallback>
                    <world>
                        <x>360</x>
                        <y>708</y>
                        <z>0</z>
                        <width>516</width>
                        <height>110</height>
                        <depth>0</depth>
                        <hotspotX>0.5</hotspotX>
                        <hotspotY>0.5</hotspotY>
                        <angle>0</angle>
                        <opacity>1</opacity>
                    </world>
                </instance>
                <instance type="AmericaDoSul" uid="19">
                    <properties>
                        <text></text>
                        <initial-visibility>Visible</initial-visibility>
                        <font>Century Gothic,-24,400,0</font>
                        <color>0,0,0</color>
                        <horizontal-alignment>Center</horizontal-alignment>
                        <vertical-alignment>Center</vertical-alignment>
                        <hotspot>Center</hotspot>
                        <wrapping>Word</wrapping>
                        <line-height>0</line-height>
                    </properties>
                    <blend-mode>0</blend-mode>
                    <effect-fallback>0</effect-fallback>
                    <world>
                        <x>355</x>
                        <y>982</y>
                        <z>0</z>
                        <width>516</width>
                        <height>110</height>
                        <depth>0</depth>
                        <hotspotX>0.5</hotspotX>
                        <hotspotY>0.5</hotspotY>
                        <angle>0</angle>
                        <opacity>1</opacity>
                    </world>
                </instance>
                <instance type="BackPergunta1" uid="24">
                    <properties>
                        <initial-visibility>Visible</initial-visibility>
                        <initial-animation>Default</initial-animation>
                        <initial-frame>0</initial-frame>
                        <collisions>Enabled</collisions>
                    </properties>
                    <blend-mode>0</blend-mode>
                    <effect-fallback>0</effect-fallback>
                    <world>
                        <x>360</x>
                        <y>981</y>
                        <z>0</z>
                        <width>616</width>
                        <height>110</height>
                        <depth>0</depth>
                        <hotspotX>0.5</hotspotX>
                        <hotspotY>0.5</hotspotY>
                        <angle>0</angle>
                        <opacity>1</opacity>
                    </world>
                </instance>
                <instance type="Resposta3" uid="18">
                    <properties>
                        <text></text>
                        <initial-visibility>Visible</initial-visibility>
                        <font>Century Gothic,-24,400,0</font>
                        <color>0,0,0</color>
                        <horizontal-alignment>Center</horizontal-alignment>
                        <vertical-alignment>Center</vertical-alignment>
                        <hotspot>Center</hotspot>
                        <wrapping>Word</wrapping>
                        <line-height>0</line-height>
                    </properties>
                    <blend-mode>0</blend-mode>
                    <effect-fallback>0</effect-fallback>
                    <world>
                        <x>360</x>
                        <y>845</y>
                        <z>0</z>
                        <width>516</width>
                        <height>110</height>
                        <depth>0</depth>
                        <hotspotX>0.5</hotspotX>
                        <hotspotY>0.5</hotspotY>
                        <angle>0</angle>
                        <opacity>1</opacity>
                    </world>
                </instance>
                <instance type="Resposta4" uid="28">
                    <properties>
                        <text></text>
                        <initial-visibility>Visible</initial-visibility>
                        <font>Century Gothic,-24,400,0</font>
                        <color>0,0,0</color>
                        <horizontal-alignment>Center</horizontal-alignment>
                        <vertical-alignment>Center</vertical-alignment>
                        <hotspot>Center</hotspot>
                        <wrapping>Word</wrapping>
                        <line-height>0</line-height>
                    </properties>
                    <blend-mode>0</blend-mode>
                    <effect-fallback>0</effect-fallback>
                    <world>
                        <x>362</x>
                        <y>983</y>
                        <z>0</z>
                        <width>516</width>
                        <height>110</height>
                        <depth>0</depth>
                        <hotspotX>0.5</hotspotX>
                        <hotspotY>0.5</hotspotY>
                        <angle>0</angle>
                        <opacity>1</opacity>
                    </world>
                </instance>
                <instance type="Resposta1" uid="29">
                    <properties>
                        <text></text>
                        <initial-visibility>Visible</initial-visibility>
                        <font>Century Gothic,-24,400,0</font>
                        <color>0,0,0</color>
                        <horizontal-alignment>Center</horizontal-alignment>
                        <vertical-alignment>Center</vertical-alignment>
                        <hotspot>Center</hotspot>
                        <wrapping>Word</wrapping>
                        <line-height>0</line-height>
                    </properties>
                    <blend-mode>0</blend-mode>
                    <effect-fallback>0</effect-fallback>
                    <world>
                        <x>358</x>
                        <y>584</y>
                        <z>0</z>
                        <width>516</width>
                        <height>110</height>
                        <depth>0</depth>
                        <hotspotX>0.5</hotspotX>
                        <hotspotY>0.5</hotspotY>
                        <angle>0</angle>
                        <opacity>1</opacity>
                    </world>
                </instance>
                <instance type="Score" uid="57">
                    <properties>
                        <text>Pontos:</text>
                        <initial-visibility>Visible</initial-visibility>
                        <font>Century Gothic,-35,700,0</font>
                        <color>0,0,0</color>
                        <horizontal-alignment>Left</horizontal-alignment>
                        <vertical-alignment>Top</vertical-alignment>
                        <hotspot>Top-left</hotspot>
                        <wrapping>Word</wrapping>
                        <line-height>0</line-height>
                    </properties>
                    <blend-mode>0</blend-mode>
                    <effect-fallback>0</effect-fallback>
                    <world>
                        <x>35</x>
                        <y>1113</y>
                        <z>0</z>
                        <width>227</width>
                        <height>75</height>
                        <depth>0</depth>
                        <hotspotX>0</hotspotX>
                        <hotspotY>0</hotspotY>
                        <angle>0</angle>
                        <opacity>1</opacity>
                    </world>
                </instance>
                <instance type="Tempo" uid="65">
                    <properties>
                        <text>Tempo:</text>
                        <initial-visibility>Visible</initial-visibility>
                        <font>Century Gothic,-35,700,0</font>
                        <color>0,0,0</color>
                        <horizontal-alignment>Left</horizontal-alignment>
                        <vertical-alignment>Top</vertical-alignment>
                        <hotspot>Top-left</hotspot>
                        <wrapping>Word</wrapping>
                        <line-height>0</line-height>
                    </properties>
                    <blend-mode>0</blend-mode>
                    <effect-fallback>0</effect-fallback>
                    <world>
                        <x>434</x>
                        <y>1113</y>
                        <z>0</z>
                        <width>227</width>
                        <height>75</height>
                        <depth>0</depth>
                        <hotspotX>0</hotspotX>
                        <hotspotY>0</hotspotY>
                        <angle>0</angle>
                        <opacity>1</opacity>
                    </world>
                </instance>
                <instance type="Fechar" uid="140">
                    <properties>
                        <initial-visibility>Visible</initial-visibility>
                        <initial-animation>Default</initial-animation>
                        <initial-frame>0</initial-frame>
                        <collisions>Enabled</collisions>
                    </properties>
                    <behavior-instances>
                        <behavior-instance type="Anchor">
                            <properties>
                                <left-edge>Window left</left-edge>
                                <top-edge>Window top</top-edge>
                                <right-edge>None</right-edge>
                                <bottom-edge>None</bottom-edge>
                                <initial-state>Enabled</initial-state>
                            </properties>
                        </behavior-instance>
                    </behavior-instances>
                    <blend-mode>0</blend-mode>
                    <effect-fallback>0</effect-fallback>
                    <world>
                        <x>653</x>
                        <y>77</y>
                        <z>0</z>
                        <width>91</width>
                        <height>87</height>
                        <depth>0</depth>
                        <hotspotX>0.5</hotspotX>
                        <hotspotY>0.5</hotspotY>
                        <angle>0</angle>
                        <opacity>1</opacity>
                    </world>
                </instance>
            </instances>
            <effects />
        </layer>
    </layers>
    <nonworld-instances>
        <instance type="Array" uid="7">
            <properties>
                <width>10</width>
                <height>1</height>
                <depth>1</depth>
            </properties>
        </instance>
    </nonworld-instances>
    <effects />
</c2layout>
